sia_app/__init__.py
sia_app/__main__.py
sia_app/assets/images/contourmap-example.png
sia_app/assets/images/currents-chart-example.png
sia_app/assets/images/heatmap-example.png
sia_app/assets/images/map-example-2.png
sia_app/assets/images/map-example.png
sia_app/assets/images/sia-logo.ico
sia_app/assets/images/sia-logo.png
sia_app/assets/images/time-series-example.png
sia_app/assets/images/unicaribe_logo.png
sia_app/assets/images/vertical-profile-example.png
sia_app/assets/images/vertical-slice-example.png
sia_app/assets/images/windrose-example.png
sia_app/assets/others/windows_installer_icon.ico
sia_app/etc/config.ini
sia_app/etc/config.ini.example
sia_app/utils/__init__.py
sia_app/utils/basic_form_fields.py
sia_app/utils/dataset_utils.py
sia_app/utils/general_utils.py
sia_app/utils/global_constants.py
sia_app/utils/global_variables.py
sia_app/utils/project_manager.py
sia_app/views/__init__.py
sia_app/views/about_app_view.py
sia_app/views/data_extractor_view.py
sia_app/views/dataset_info_view.py
sia_app/views/home_view.py
sia_app/views/new_project_view.py
sia_app/views/user_manual_view.py
sia_app/views/workspace_view.py
sia_app/views/charts/__init__.py
sia_app/views/charts/contour_map_view.py
sia_app/views/charts/currents_views.py
sia_app/views/charts/heatmap_view.py
sia_app/views/charts/single_point_time_series_view.py
sia_app/views/charts/single_point_vertical_profile_view.py
sia_app/views/charts/vertical_slice_view.py
sia_app/views/charts/wind_rose_view.py
sia_app/views/templates/__init__.py
sia_app/views/templates/scrollable_view.py
sia_app/views/templates/tab_view.py
sia_app/widgets/__init__.py
sia_app/widgets/own_widgets.py
sia_app-1.1.0.dist-info/COPYING
sia_app-1.1.0.dist-info/METADATA
sia_app-1.1.0.dist-info/WHEEL
sia_app-1.1.0.dist-info/entry_points.txt
sia_app-1.1.0.dist-info/top_level.txt
sia_app-1.1.0.dist-info/RECORD
