Metadata-Version: 2.1
Name: sia-app
Version: 1.1.0
Summary: Application to facilitate the download, exploration and visual analysis of oceanographic data.
Author: Alexis Montejo, Julian Maldonado et al.
Maintainer: SIA Project
License: GNU GENERAL PUBLIC LICENSE
Project-URL: Homepage, https://sia-information-system.github.io/sia-website
Project-URL: Source Code, https://github.com/sia-information-system/sia-desktop-app
Keywords: gis,cartography,oceanographic,oceanic,data,visualization,extraction,etl,analysis
Requires-Python: >=3.10
License-File: COPYING
Requires-Dist: ttkbootstrap (>=1.10.1)
Requires-Dist: siaextractlib (>=0.2.2)
Requires-Dist: siaplotlib (>=0.2.1)
Requires-Dist: pillow (>=9.3.0)
Requires-Dist: xarray (>=2023.5.0)
Requires-Dist: numpy (>=1.23.4)
Provides-Extra: dev
Requires-Dist: bumpver ; extra == 'dev'
Requires-Dist: build ; extra == 'dev'
Requires-Dist: twine ; extra == 'dev'
